numberextractor/__init__.py
numberextractor/extract.py
numberextractor-0.0.1.dist-info/METADATA
numberextractor-0.0.1.dist-info/WHEEL
numberextractor-0.0.1.dist-info/top_level.txt
numberextractor-0.0.1.dist-info/RECORD
